{"slug":"cuando-la-isla-vive-en-la-sangre-nostalgia-memoria-orgullo-boricua","title":"Cuando la isla vive en la sangre — nostalgia, memoria y orgullo boricua","excerpt":"La nostalgia boricua no es tristeza — es memoria cultural activa. Lo que significa llevar a Puerto Rico en la sangre desde cualquier rincón del mundo.","category":"Identidad Boricua","date":"3 de marzo de 2026","dateISO":"2026-03-03","readTime":"5","image":"/img/carry-on-boricua.jpg","tags":["nostalgia boricua","identidad","diáspora","memoria cultural","Puerto Rico"],"content":"<p>Estaba en el supermercado en Chicago un martes de febrero. Y entonces, de algún pasillo, llegó un olor que tenía la misma temperatura emocional que el café colao de la casa de su abuela en Caguas.</p><p>Antes de que pudiera procesarlo, el cuerpo ya había respondido. Un segundo de quietud completa. Los ojos un poco húmedos sin razón aparente. Así funciona la memoria cultural. No avisa. No pide permiso.</p><hr><h2>No es tristeza — es pertenencia estirada por la distancia</h2><p>La nostalgia boricua no es debilidad. Es memoria cultural activa — el mismo mecanismo que permitió que la música africana sobreviviera y se convirtiera en bomba y plena en el <strong>Planeta Boricua</strong>.</p><hr><h2>El corazón boricua no se muda. Se expande.</h2><p>Ser boricua no depende de dónde estés parado. Depende de lo que decides recordar, cuidar y pasar adelante. Siendo siempre <strong>más boricua que un mofongo</strong>. 🇵🇷</p><p><a href='/'>Explora Planeta Boricua →</a></p>"}
